lytools/__init__.py
lytools/_lytools.py
lytools/test.py
lytools-0.0.128.dist-info/licenses/LICENSE
lytools-0.0.128.dist-info/METADATA
lytools-0.0.128.dist-info/WHEEL
lytools-0.0.128.dist-info/top_level.txt
lytools-0.0.128.dist-info/RECORD
