Metadata-Version: 2.4
Name: lytools
Version: 0.0.128
Home-page: https://github.com/leeyang1991/lytools
Author: Yang Li
Author-email: leeyang1991@gmail.com
Requires-Python: >=3
License-File: LICENSE
Requires-Dist: matplotlib
Requires-Dist: numpy
Requires-Dist: scipy
Requires-Dist: gdal
Requires-Dist: tqdm
Requires-Dist: pandas
Requires-Dist: seaborn
Requires-Dist: scikit-learn
Requires-Dist: basemap
Requires-Dist: netCDF4
Requires-Dist: psutil
Requires-Dist: openpyxl
Dynamic: author
Dynamic: author-email
Dynamic: description
Dynamic: description-content-type
Dynamic: home-page
Dynamic: license-file
Dynamic: requires-dist
Dynamic: requires-python
